digitcolumngraph/__init__.py
digitcolumngraph/digitcolumngraph.py
digitcolumngraph-0.0.6.dist-info/DESCRIPTION.rst
digitcolumngraph-0.0.6.dist-info/METADATA
digitcolumngraph-0.0.6.dist-info/RECORD
digitcolumngraph-0.0.6.dist-info/WHEEL
digitcolumngraph-0.0.6.dist-info/metadata.json
digitcolumngraph-0.0.6.dist-info/top_level.txt
